yoloexplorer/__init__.py
yoloexplorer/dataset.py
yoloexplorer/explorer.py
yoloexplorer/yolo_predictor.py
yoloexplorer-0.0.1.dev1.dist-info/METADATA
yoloexplorer-0.0.1.dev1.dist-info/WHEEL
yoloexplorer-0.0.1.dev1.dist-info/top_level.txt
yoloexplorer-0.0.1.dev1.dist-info/RECORD
