Metadata-Version: 2.1
Name: yoloexplorer
Version: 0.0.1.dev1
Author: dev@lance
Author-email: contact@lancedb.com
Requires-Python: >=3.8
Requires-Dist: lancedb
Requires-Dist: duckdb
Requires-Dist: scikit-learn
Requires-Dist: ultralytics
